{
	"databaseType": "Sybase",
	"inputEntity": [
	],
	"inputParameters": [
		{
			"attributeId": "",
			"bddType": "varchar",
			"dataType": "VARCHAR",
			"direction": "in",
			"entityId": "",
			"format": "",
			"name": "@i_banco",
			"type": "CUSTOM",
			"value": "operation"
		},
		{
			"attributeId": "",
			"bddType": "int",
			"dataType": "INT",
			"direction": "in",
			"entityId": "",
			"format": "",
			"name": "@i_tramite",
			"type": "CUSTOM",
			"value": "numProcedure"
		},
		{
			"attributeId": "",
			"bddType": "int",
			"dataType": "INT",
			"direction": "in",
			"entityId": "",
			"format": "",
			"name": "@i_cliente",
			"type": "CUSTOM",
			"value": "numIdentification"
		},
		{
			"attributeId": "",
			"bddType": "smallint",
			"dataType": "SMALLINT",
			"direction": "in",
			"entityId": "",
			"format": "",
			"name": "@i_oficina",
			"type": "CUSTOM",
			"value": "office"
		},
		{
			"attributeId": "",
			"bddType": "tinyint",
			"dataType": "TINYINT",
			"direction": "in",
			"entityId": "",
			"format": "",
			"name": "@i_moneda",
			"type": "CUSTOM",
			"value": "currency"
		},
		{
			"attributeId": "",
			"bddType": "datetime",
			"dataType": "DATETIME",
			"direction": "in",
			"entityId": "",
			"format": "",
			"name": "@i_fecha_ini",
			"type": "CUSTOM",
			"value": "disbursementDate"
		},
		{
			"attributeId": "",
			"bddType": "varchar",
			"dataType": "VARCHAR",
			"direction": "in",
			"entityId": "",
			"format": "",
			"name": "@i_toperacion",
			"type": "CUSTOM",
			"value": "type"
		},
		{
			"attributeId": "",
			"bddType": "varchar",
			"dataType": "VARCHAR",
			"direction": "in",
			"entityId": "",
			"format": "",
			"name": "@i_estado",
			"type": "CUSTOM",
			"value": "state"
		},
		{
			"attributeId": "",
			"bddType": "varchar",
			"dataType": "VARCHAR",
			"direction": "in",
			"entityId": "",
			"format": "",
			"name": "@i_migrada",
			"type": "CUSTOM",
			"value": "migratedOperation"
		},
		{
			"attributeId": "",
			"bddType": "int",
			"dataType": "INT",
			"direction": "in",
			"entityId": "",
			"format": "",
			"name": "@i_formato_fecha",
			"type": "CONSTANT",
			"value": "103"
		},
		{
			"attributeId": "",
			"bddType": "tinyint",
			"dataType": "TINYINT",
			"direction": "in",
			"entityId": "",
			"format": "",
			"name": "@i_condicion_est",
			"type": "CUSTOM",
			"value": "condition"
		},
		{
			"attributeId": "",
			"bddType": "int",
			"dataType": "INT",
			"direction": "in",
			"entityId": "",
			"format": "",
			"name": "@t_trn",
			"type": "CONSTANT",
			"value": "7130"
		},
		{
			"attributeId": "",
			"bddType": "varchar",
			"dataType": "VARCHAR",
			"direction": "in",
			"entityId": "",
			"format": "",
			"name": "@i_web",
			"type": "CONSTANT",
			"value": "S"
		},
		{
			"attributeId": "",
			"bddType": "varchar",
			"dataType": "VARCHAR",
			"direction": "in",
			"entityId": "",
			"format": "",
			"name": "@i_grupal",
			"type": "CONSTANT",
			"value": "N"
		},
		{
			"attributeId": "",
			"bddType": "int",
			"dataType": "INT",
			"direction": "in",
			"entityId": "",
			"format": "",
			"name": "@i_categoria",
			"type": "CUSTOM",
			"value": "categoryGroup"
		}
	],
	"name": "BLI_LoanSearchReajustes",
	"outputEntity": [
	],
	"outputParameters": [
	],
	"patternId": "BLI5241_bli_loansearchreajustes",
	"patternName": "BLI_LoanSearchReajustes",
	"patternType": "Bli",
	"queries": [
		{
			"_idQuery": "1c722065-9115-46c7-bac9-45c986a712c8",
			"isMapReturn": true,
			"isReturn": true,
			"isSingleResult": false,
			"numberQuery": 1,
			"queryName": "SELECT"
		}
	],
	"resultSets": [
		{
			"_idQuery": "1c722065-9115-46c7-bac9-45c986a712c8",
			"columns": [
				{
					"attributeId": "AT72_OPERATOI654",
					"entityId": "EN_READJUSNN_654",
					"format": "",
					"name": "No.Operacion",
					"position": 3,
					"type": "ATTRIBUTE"
				},
				{
					"attributeId": "AT79_CLIENTDT654",
					"entityId": "EN_READJUSNN_654",
					"format": "",
					"name": "Cliente",
					"position": 5,
					"type": "ATTRIBUTE"
				}
			],
			"number": 1,
			"singleResult": false
		}
	],
	"returnEntity": [
		{
			"entityId": "EN_READJUSNN_654",
			"module": {
				"moduleId": "LNSPR",
				"moduleName": "LOANSOPERATION"
			},
			"name": "ReadjustmenMList"
		}
	],
	"serverName": "CENTRAL",
	"serviceID": "cob_cartera.sp_buscar_operaciones",
	"type": "SP",
	"typeMapping": "MAPJava"
}
