{
	"_transient": null,
	"attributes": {
		"AT19_TIPOYEPX741": {
			"attributeId": "AT19_TIPOYEPX741",
			"autoGeneratedStr": "F",
			"columnName": null,
			"customizationLayer": 0,
			"customizationLayerDescription": "ECU",
			"dataType": "Char",
			"entityPk": {
				"entityId": "EN_DETAILNEO_741",
				"version": "1.0.0"
			},
			"expression": null,
			"falseValue": null,
			"labelId": null,
			"length": 3,
			"listValues": null,
			"name": "tipo",
			"objectType": null,
			"order": 1,
			"pkStr": "F",
			"requiredStr": "F",
			"transientStr": "F",
			"trueValue": null
		},
		"AT31_CONCEPTO741": {
			"attributeId": "AT31_CONCEPTO741",
			"autoGeneratedStr": "F",
			"columnName": null,
			"customizationLayer": 0,
			"customizationLayerDescription": "ECU",
			"dataType": "String",
			"entityPk": {
				"entityId": "EN_DETAILNEO_741",
				"version": "1.0.0"
			},
			"expression": null,
			"falseValue": null,
			"labelId": null,
			"length": 0,
			"listValues": null,
			"name": "concepto",
			"objectType": null,
			"order": 2,
			"pkStr": "F",
			"requiredStr": "F",
			"transientStr": "F",
			"trueValue": null
		},
		"AT32_MONTOMGG741": {
			"attributeId": "AT32_MONTOMGG741",
			"autoGeneratedStr": "F",
			"columnName": null,
			"customizationLayer": 0,
			"customizationLayerDescription": "ECU",
			"dataType": "Double",
			"entityPk": {
				"entityId": "EN_DETAILNEO_741",
				"version": "1.0.0"
			},
			"expression": null,
			"falseValue": null,
			"labelId": null,
			"length": 0,
			"listValues": null,
			"name": "montoMPG",
			"objectType": null,
			"order": 5,
			"pkStr": "F",
			"requiredStr": "F",
			"transientStr": "F",
			"trueValue": null
		},
		"AT53_MONEDAKA741": {
			"attributeId": "AT53_MONEDAKA741",
			"autoGeneratedStr": "F",
			"columnName": null,
			"customizationLayer": 0,
			"customizationLayerDescription": "ECU",
			"dataType": "Integer",
			"entityPk": {
				"entityId": "EN_DETAILNEO_741",
				"version": "1.0.0"
			},
			"expression": null,
			"falseValue": null,
			"labelId": null,
			"length": 0,
			"listValues": null,
			"name": "moneda",
			"objectType": null,
			"order": 4,
			"pkStr": "F",
			"requiredStr": "F",
			"transientStr": "F",
			"trueValue": null
		},
		"AT53_MONTOMOP741": {
			"attributeId": "AT53_MONTOMOP741",
			"autoGeneratedStr": "F",
			"columnName": null,
			"customizationLayer": 0,
			"customizationLayerDescription": "ECU",
			"dataType": "Double",
			"entityPk": {
				"entityId": "EN_DETAILNEO_741",
				"version": "1.0.0"
			},
			"expression": null,
			"falseValue": null,
			"labelId": null,
			"length": 0,
			"listValues": null,
			"name": "montoMOP",
			"objectType": null,
			"order": 6,
			"pkStr": "F",
			"requiredStr": "F",
			"transientStr": "F",
			"trueValue": null
		},
		"AT77_CUENTACZ741": {
			"attributeId": "AT77_CUENTACZ741",
			"autoGeneratedStr": "F",
			"columnName": null,
			"customizationLayer": 0,
			"customizationLayerDescription": "ECU",
			"dataType": "String",
			"entityPk": {
				"entityId": "EN_DETAILNEO_741",
				"version": "1.0.0"
			},
			"expression": null,
			"falseValue": null,
			"labelId": null,
			"length": 0,
			"listValues": null,
			"name": "cuenta",
			"objectType": null,
			"order": 3,
			"pkStr": "F",
			"requiredStr": "F",
			"transientStr": "F",
			"trueValue": null
		}
	},
	"customizationLayer": 0,
	"customizationLayerDescription": "ECU",
	"databaseName": null,
	"dbmsName": null,
	"description": null,
	"id": {
		"entityId": "EN_DETAILNEO_741",
		"version": "1.0.0"
	},
	"isAutomatic": false,
	"isImported": false,
	"moduleId": "ASSTS",
	"name": {
		"$ref": "../../ASSTS/relations/componentKeys.json#/Entities/EN_DETAILNEO_741/name"
	},
	"related": false,
	"tableName": null,
	"transient": null
}
