{
	"_transient": null,
	"attributes": {
		"AT11_CODEXORG418": {
			"attributeId": "AT11_CODEXORG418",
			"autoGeneratedStr": "F",
			"columnName": null,
			"customizationLayer": 0,
			"customizationLayerDescription": "ECU",
			"dataType": "String",
			"entityPk": {
				"entityId": "EN_OPERATINU_418",
				"version": "1.0.0"
			},
			"expression": null,
			"falseValue": null,
			"labelId": null,
			"length": 0,
			"listValues": null,
			"name": "code",
			"objectType": null,
			"order": 4,
			"pkStr": "F",
			"requiredStr": "F",
			"transientStr": "F",
			"trueValue": null
		},
		"AT18_IDNUMBEE418": {
			"attributeId": "AT18_IDNUMBEE418",
			"autoGeneratedStr": "F",
			"columnName": null,
			"customizationLayer": 0,
			"customizationLayerDescription": "ECU",
			"dataType": "String",
			"entityPk": {
				"entityId": "EN_OPERATINU_418",
				"version": "1.0.0"
			},
			"expression": null,
			"falseValue": null,
			"labelId": null,
			"length": 0,
			"listValues": null,
			"name": "idNumber",
			"objectType": null,
			"order": 3,
			"pkStr": "F",
			"requiredStr": "F",
			"transientStr": "F",
			"trueValue": null
		},
		"AT26_COMPANYY418": {
			"attributeId": "AT26_COMPANYY418",
			"autoGeneratedStr": "F",
			"columnName": null,
			"customizationLayer": 0,
			"customizationLayerDescription": "ECU",
			"dataType": "Integer",
			"entityPk": {
				"entityId": "EN_OPERATINU_418",
				"version": "1.0.0"
			},
			"expression": null,
			"falseValue": null,
			"labelId": null,
			"length": 0,
			"listValues": null,
			"name": "company",
			"objectType": null,
			"order": 5,
			"pkStr": "F",
			"requiredStr": "F",
			"transientStr": "F",
			"trueValue": null
		},
		"AT47_FULLNAME418": {
			"attributeId": "AT47_FULLNAME418",
			"autoGeneratedStr": "F",
			"columnName": null,
			"customizationLayer": 0,
			"customizationLayerDescription": "ECU",
			"dataType": "String",
			"entityPk": {
				"entityId": "EN_OPERATINU_418",
				"version": "1.0.0"
			},
			"expression": null,
			"falseValue": null,
			"labelId": null,
			"length": 255,
			"listValues": null,
			"name": "fullName",
			"objectType": null,
			"order": 2,
			"pkStr": "F",
			"requiredStr": "F",
			"transientStr": "F",
			"trueValue": null
		},
		"AT59_OFFICERR418": {
			"attributeId": "AT59_OFFICERR418",
			"autoGeneratedStr": "F",
			"columnName": null,
			"customizationLayer": 0,
			"customizationLayerDescription": "ECU",
			"dataType": "String",
			"entityPk": {
				"entityId": "EN_OPERATINU_418",
				"version": "1.0.0"
			},
			"expression": null,
			"falseValue": null,
			"labelId": null,
			"length": 0,
			"listValues": null,
			"name": "officer",
			"objectType": null,
			"order": 7,
			"pkStr": "F",
			"requiredStr": "F",
			"transientStr": "F",
			"trueValue": null
		},
		"AT71_SUBTYPEE418": {
			"attributeId": "AT71_SUBTYPEE418",
			"autoGeneratedStr": "F",
			"columnName": null,
			"customizationLayer": 0,
			"customizationLayerDescription": "ECU",
			"dataType": "String",
			"entityPk": {
				"entityId": "EN_OPERATINU_418",
				"version": "1.0.0"
			},
			"expression": null,
			"falseValue": null,
			"labelId": null,
			"length": 0,
			"listValues": null,
			"name": "subType",
			"objectType": null,
			"order": 6,
			"pkStr": "F",
			"requiredStr": "F",
			"transientStr": "F",
			"trueValue": null
		},
		"AT73_ROLELEJK418": {
			"attributeId": "AT73_ROLELEJK418",
			"autoGeneratedStr": "F",
			"columnName": null,
			"customizationLayer": 0,
			"customizationLayerDescription": "ECU",
			"dataType": "Boolean",
			"entityPk": {
				"entityId": "EN_OPERATINU_418",
				"version": "1.0.0"
			},
			"expression": null,
			"falseValue": null,
			"labelId": null,
			"length": 0,
			"listValues": null,
			"name": "role",
			"objectType": null,
			"order": 1,
			"pkStr": "F",
			"requiredStr": "F",
			"transientStr": "F",
			"trueValue": null
		}
	},
	"customizationLayer": 0,
	"customizationLayerDescription": "ECU",
	"databaseName": null,
	"dbmsName": null,
	"description": null,
	"enableAutoCRUD": null,
	"id": {
		"entityId": "EN_OPERATINU_418",
		"version": "1.0.0"
	},
	"isAutomatic": false,
	"isImported": false,
	"moduleId": "ASSTS",
	"name": {
		"$ref": "../../ASSTS/relations/componentKeys.json#/Entities/EN_OPERATINU_418/name"
	},
	"related": false,
	"tableName": null,
	"transient": null
}
