{
	"_transient": null,
	"attributes": {
		"AT39_OPERATON653": {
			"attributeId": "AT39_OPERATON653",
			"autoGeneratedStr": "F",
			"columnName": null,
			"customizationLayer": 0,
			"customizationLayerDescription": "ECU",
			"dataType": "String",
			"entityPk": {
				"entityId": "EN_REVERSEDO_653",
				"version": "1.0.0"
			},
			"expression": null,
			"falseValue": null,
			"labelId": null,
			"length": 0,
			"listValues": null,
			"name": "operation",
			"objectType": null,
			"order": 3,
			"pkStr": "F",
			"requiredStr": "F",
			"transientStr": "F",
			"trueValue": null
		},
		"AT50_DATETRTT653": {
			"attributeId": "AT50_DATETRTT653",
			"autoGeneratedStr": "F",
			"columnName": null,
			"customizationLayer": 0,
			"customizationLayerDescription": "ECU",
			"dataType": "String",
			"entityPk": {
				"entityId": "EN_REVERSEDO_653",
				"version": "1.0.0"
			},
			"expression": null,
			"falseValue": null,
			"labelId": null,
			"length": 0,
			"listValues": null,
			"name": "dateTransaction",
			"objectType": null,
			"order": 4,
			"pkStr": "F",
			"requiredStr": "F",
			"transientStr": "F",
			"trueValue": null
		},
		"AT60_STAREUIZ653": {
			"attributeId": "AT60_STAREUIZ653",
			"autoGeneratedStr": "F",
			"columnName": null,
			"customizationLayer": 0,
			"customizationLayerDescription": "ECU",
			"dataType": "String",
			"entityPk": {
				"entityId": "EN_REVERSEDO_653",
				"version": "1.0.0"
			},
			"expression": null,
			"falseValue": null,
			"labelId": null,
			"length": 0,
			"listValues": null,
			"name": "stare",
			"objectType": null,
			"order": 6,
			"pkStr": "F",
			"requiredStr": "F",
			"transientStr": "F",
			"trueValue": null
		},
		"AT64_USERMIJC653": {
			"attributeId": "AT64_USERMIJC653",
			"autoGeneratedStr": "F",
			"columnName": null,
			"customizationLayer": 0,
			"customizationLayerDescription": "ECU",
			"dataType": "String",
			"entityPk": {
				"entityId": "EN_REVERSEDO_653",
				"version": "1.0.0"
			},
			"expression": null,
			"falseValue": null,
			"labelId": null,
			"length": 0,
			"listValues": null,
			"name": "user",
			"objectType": null,
			"order": 7,
			"pkStr": "F",
			"requiredStr": "F",
			"transientStr": "F",
			"trueValue": null
		},
		"AT67_TRANSAIN653": {
			"attributeId": "AT67_TRANSAIN653",
			"autoGeneratedStr": "F",
			"columnName": null,
			"customizationLayer": 0,
			"customizationLayerDescription": "ECU",
			"dataType": "String",
			"entityPk": {
				"entityId": "EN_REVERSEDO_653",
				"version": "1.0.0"
			},
			"expression": null,
			"falseValue": null,
			"labelId": null,
			"length": 0,
			"listValues": null,
			"name": "transaction",
			"objectType": null,
			"order": 1,
			"pkStr": "F",
			"requiredStr": "F",
			"transientStr": "F",
			"trueValue": null
		},
		"AT85_SECUENII653": {
			"attributeId": "AT85_SECUENII653",
			"autoGeneratedStr": "F",
			"columnName": null,
			"customizationLayer": 0,
			"customizationLayerDescription": "ECU",
			"dataType": "Integer",
			"entityPk": {
				"entityId": "EN_REVERSEDO_653",
				"version": "1.0.0"
			},
			"expression": null,
			"falseValue": null,
			"labelId": null,
			"length": 0,
			"listValues": null,
			"name": "secuential",
			"objectType": null,
			"order": 2,
			"pkStr": "F",
			"requiredStr": "F",
			"transientStr": "F",
			"trueValue": null
		},
		"AT92_OBSERVTI653": {
			"attributeId": "AT92_OBSERVTI653",
			"autoGeneratedStr": "F",
			"columnName": null,
			"customizationLayer": 0,
			"customizationLayerDescription": "ECU",
			"dataType": "String",
			"entityPk": {
				"entityId": "EN_REVERSEDO_653",
				"version": "1.0.0"
			},
			"expression": null,
			"falseValue": null,
			"labelId": null,
			"length": 0,
			"listValues": null,
			"name": "observation",
			"objectType": null,
			"order": 8,
			"pkStr": "F",
			"requiredStr": "F",
			"transientStr": "F",
			"trueValue": null
		},
		"AT94_DATERERR653": {
			"attributeId": "AT94_DATERERR653",
			"autoGeneratedStr": "F",
			"columnName": null,
			"customizationLayer": 0,
			"customizationLayerDescription": "ECU",
			"dataType": "String",
			"entityPk": {
				"entityId": "EN_REVERSEDO_653",
				"version": "1.0.0"
			},
			"expression": null,
			"falseValue": null,
			"labelId": null,
			"length": 0,
			"listValues": null,
			"name": "dateReverd",
			"objectType": null,
			"order": 5,
			"pkStr": "F",
			"requiredStr": "F",
			"transientStr": "F",
			"trueValue": null
		}
	},
	"customizationLayer": 0,
	"customizationLayerDescription": "ECU",
	"databaseName": null,
	"dbmsName": null,
	"description": null,
	"id": {
		"entityId": "EN_REVERSEDO_653",
		"version": "1.0.0"
	},
	"isAutomatic": false,
	"isImported": false,
	"moduleId": "ASSTS",
	"name": {
		"$ref": "../../ASSTS/relations/componentKeys.json#/Entities/EN_REVERSEDO_653/name"
	},
	"related": false,
	"tableName": null,
	"transient": null
}
